h5pxblock/__init__.py
h5pxblock/h5pxblock.py
h5pxblock/utils.py
h5pxblock/public/js/h5pcustom.js
h5pxblock/static/css/student_view.css
h5pxblock/static/css/studio.css
h5pxblock/static/html/h5pxblock.html
h5pxblock/static/html/studio.html
h5pxblock/static/js/src/h5pxblock.js
h5pxblock/static/js/src/installRequired.js
h5pxblock/static/js/src/studio.js
h5pxblock/translations/__init__.py
h5pxblock/translations/config.yaml
h5pxblock/translations/ar/LC_MESSAGES/text.mo
h5pxblock/translations/ar/LC_MESSAGES/text.po
h5pxblock/translations/en/LC_MESSAGES/text.mo
h5pxblock/translations/en/LC_MESSAGES/text.po
h5pxblock/translations/es_419/LC_MESSAGES/text.mo
h5pxblock/translations/es_419/LC_MESSAGES/text.po
h5pxblock/translations/es_ES/LC_MESSAGES/text.mo
h5pxblock/translations/es_ES/LC_MESSAGES/text.po
h5pxblock/translations/fa/LC_MESSAGES/text.mo
h5pxblock/translations/fa/LC_MESSAGES/text.po
h5pxblock/translations/pt_PT/LC_MESSAGES/text.mo
h5pxblock/translations/pt_PT/LC_MESSAGES/text.po
h5p_xblock-0.2.17.dist-info/LICENSE
h5p_xblock-0.2.17.dist-info/METADATA
h5p_xblock-0.2.17.dist-info/WHEEL
h5p_xblock-0.2.17.dist-info/entry_points.txt
h5p_xblock-0.2.17.dist-info/top_level.txt
h5p_xblock-0.2.17.dist-info/RECORD
