Metadata-Version: 2.2
Name: h5p-xblock
Version: 0.2.17
Summary: XBlock to play self hosted h5p content inside open edX
Home-page: https://github.com/edly-io/h5pxblock
Author: edly
Author-email: hello@edly.io
License: MIT
Keywords: python edx h5p xblock
Classifier: Development Status :: 4 - Beta
Classifier: Framework :: Django
Classifier: Framework :: Django :: 3.2
Classifier: Framework :: Django :: 4.0
Classifier: Intended Audience :: Developers
Classifier: License :: OSI Approved :: MIT License
Classifier: Natural Language :: English
Classifier: Programming Language :: Python :: 3
Classifier: Programming Language :: Python :: 3.8
License-File: LICENSE
Requires-Dist: XBlock
Dynamic: author
Dynamic: author-email
Dynamic: classifier
Dynamic: description
Dynamic: description-content-type
Dynamic: home-page
Dynamic: keywords
Dynamic: license
Dynamic: requires-dist
Dynamic: summary
